backend/__init__.py
backend/cli.py
backend/fixtures.py
backend/main.py
backend/status.py
backend/models/__init__.py
backend/models/custom_axis.py
backend/models/layer.py
backend/models/projection.py
backend/models/selection.py
backend/models/transformation.py
backend/routers/__init__.py
backend/routers/custom_axes.py
backend/routers/layers.py
backend/routers/projections.py
backend/routers/scenarios.py
backend/routers/selections.py
backend/routers/transformations.py
backend/services/__init__.py
backend/services/data_store.py
backend/services/projection_engine.py
backend/services/transform_engine.py
backend/tests/__init__.py
backend/tests/test_custom_axes.py
backend/tests/test_data_store.py
frontend_dist/__init__.py
frontend_dist/index.html
frontend_dist/logo.svg
frontend_dist/logo_no_name.svg
frontend_dist/assets/index-Brfo4QVB.js
scenarios/__init__.py
scenarios/breast_cancer_config.json
scenarios/breast_cancer_data.npz
scenarios/deep_chain_config.json
scenarios/deep_chain_data.npz
scenarios/diabetes_config.json
scenarios/diabetes_data.npz
scenarios/digits_config.json
scenarios/digits_data.npz
scenarios/example-custom-axes_config.json
scenarios/example-custom-axes_data.npz
scenarios/iris_config.json
scenarios/iris_data.npz
scenarios/linear_multi_view_config.json
scenarios/linear_multi_view_data.npz
scenarios/linear_single_view_config.json
scenarios/linear_single_view_data.npz
scenarios/synthetic_1000_config.json
scenarios/synthetic_1000_data.npz
scenarios/test_pca_config.json
scenarios/test_pca_data.npz
scenarios/wine_config.json
scenarios/wine_data.npz
vectorscope-1.2.5.dist-info/METADATA
vectorscope-1.2.5.dist-info/WHEEL
vectorscope-1.2.5.dist-info/entry_points.txt
vectorscope-1.2.5.dist-info/licenses/LICENSE
vectorscope-1.2.5.dist-info/RECORD
