Metadata-Version: 2.4
Name: vectorscope
Version: 1.2.5
Summary: Interactive vector embedding visualization and transformation system
Project-URL: Homepage, https://github.com/cranmer/vectorscope
Project-URL: Documentation, https://cranmer.github.io/vectorscope
Project-URL: Repository, https://github.com/cranmer/vectorscope
Author: Kyle Cranmer
License-Expression: MIT
License-File: LICENSE
Keywords: dimensionality-reduction,embeddings,pca,tsne,umap,visualization
Classifier: Development Status :: 4 - Beta
Classifier: Intended Audience :: Science/Research
Classifier: License :: OSI Approved :: MIT License
Classifier: Programming Language :: Python :: 3
Classifier: Programming Language :: Python :: 3.11
Classifier: Programming Language :: Python :: 3.12
Classifier: Topic :: Scientific/Engineering :: Visualization
Requires-Python: >=3.10
Requires-Dist: fastapi>=0.109
Requires-Dist: numpy>=1.26
Requires-Dist: pydantic>=2.6
Requires-Dist: python-multipart>=0.0.6
Requires-Dist: scikit-learn>=1.4
Requires-Dist: scipy>=1.12
Requires-Dist: umap-learn>=0.5
Requires-Dist: uvicorn>=0.27
Provides-Extra: dev
Requires-Dist: httpx>=0.26; extra == 'dev'
Requires-Dist: pytest>=8.0; extra == 'dev'
Provides-Extra: docs
Requires-Dist: myst-parser>=2.0; extra == 'docs'
Requires-Dist: sphinx-rtd-theme>=2.0; extra == 'docs'
Requires-Dist: sphinx>=7.0; extra == 'docs'
